<annotation>
	<folder>images</folder>
	<filename>IMG_0468.JPG</filename>
	<path>/Users/alecschwartz/Desktop/workspace/snakes/images/IMG_0468.JPG</path>
	<source>
		<database>Unknown</database>
	</source>
	<size>
		<width>2048</width>
		<height>1536</height>
		<depth>3</depth>
	</size>
	<segmented>0</segmented>
	<object>
		<name>snake</name>
		<pose>Unspecified</pose>
		<truncated>0</truncated>
		<difficult>0</difficult>
		<bndbox>
			<xmin>706</xmin>
			<ymin>994</ymin>
			<xmax>855</xmax>
			<ymax>1255</ymax>
		</bndbox>
	</object>
</annotation>
